{
  "id": 1303,
  "title": "Auckland Weekly News",
  "genre": "Newspaper",
  "firstYear": "1877",
  "finalYear": "1934",
  "district": "Auckland",
  "frequency": "Weekly",
  "idMarcControlNumber": "5092910",
  "idNZNewspapersV1": "6034",
  "isCurrent": false,
  "placecode": "02-01-auckland",
  "placename": "Auckland",
  "region": "Auckland",
  "links": {
    "1302": {
      "direction": "Continues",
      "target-description": "Weekly News and  Weekly Herald"
    },
    "1346": {
      "direction": "Continued By",
      "target-description": "Weekly News"
    }
  },
  "sources": {
    "2013-04-02T08:58:38.000Z": "Extracted from the New Zealand National Bibliography (MARC record 5092910) downloaded March 2013.",
    "2015-01-21T10:37:16.000Z": "Modified by gordon.paynter"
  },
  "revision": 6
}