{
  "stats": {
    "placename": "Ross",
    "count": 5
  },
  "papers": {
    "2329": {
      "title": "Ross Guardian and Totara Advertiser",
      "firstYear": "1868",
      "finalYear": "1879"
    },
    "2332": {
      "title": "Evening Times and Advertiser",
      "firstYear": "1870",
      "finalYear": "uuuu"
    },
    "2333": {
      "title": "Ross News",
      "firstYear": "1871",
      "finalYear": "1873"
    },
    "2336": {
      "title": "Ross and Okarito Advocate",
      "firstYear": "1880",
      "finalYear": "1908"
    },
    "2338": {
      "title": "Ross Mercury and Westland Miner",
      "firstYear": "1883",
      "finalYear": "188u"
    }
  }
}