{
  "id": 3012,
  "title": "Tabloid",
  "genre": "Duplicate",
  "firstYear": "2002",
  "finalYear": "2002",
  "district": "New Plymouth District",
  "idMarcControlNumber": "7238542",
  "idNZNewspapersV1": "14312624",
  "isCurrent": false,
  "placecode": "07-01",
  "placename": "Inglewood",
  "region": "Taranaki",
  "sources": {
    "2013-04-02T08:58:38.000Z": "Extracted from the New Zealand National Bibliography (MARC record 7238542) downloaded March 2013.",
    "2014-05-15T04:18:35.000Z": "Modified by DataBot"
  },
  "revision": 2
}