{
  "stats": {
    "placename": "Te Aroha",
    "count": 8,
    "decades": 5
  },
  "papers": [
    {
      "id": "1549",
      "title": "Te Aroha Mail",
      "firstYear": "1882",
      "finalYear": "uuuu"
    },
    {
      "id": "1550",
      "title": "Te Aroha News",
      "firstYear": "1883",
      "finalYear": "1885",
      "urlDigitized": "https://paperspast.natlib.govt.nz/newspapers/te-aroha-news"
    },
    {
      "id": "1551",
      "title": "The Aroha & Ohinemuri News",
      "firstYear": "1885",
      "finalYear": "1917",
      "urlDigitized": "https://paperspast.natlib.govt.nz/newspapers/te-aroha-news"
    },
    {
      "id": "3065",
      "title": "Aroha Gazette, Waiorongomai, Piako And Ohinemuri Advocate",
      "firstYear": "1888",
      "finalYear": "1888"
    },
    {
      "id": "1552",
      "title": "Te Aroha Times and Waiorongomai Advocate",
      "firstYear": "1896",
      "finalYear": "1898"
    },
    {
      "id": "1555",
      "title": "Te Aroha News (1917)",
      "firstYear": "1917",
      "finalYear": "1986"
    },
    {
      "id": "1559",
      "title": "Te Aroha District News for Overseas",
      "firstYear": "1941",
      "finalYear": "1945"
    },
    {
      "id": "1566",
      "title": "Te Aroha Tribune",
      "firstYear": "1989",
      "finalYear": "1990"
    }
  ]
}